db_model_trainer/__init__.py
db_model_trainer/cli.py
db_model_trainer/yaml_processor.py
db_model_trainer-0.1.2.dist-info/licenses/LICENSE
db_model_trainer-0.1.2.dist-info/METADATA
db_model_trainer-0.1.2.dist-info/WHEEL
db_model_trainer-0.1.2.dist-info/entry_points.txt
db_model_trainer-0.1.2.dist-info/top_level.txt
db_model_trainer-0.1.2.dist-info/RECORD
