Metadata-Version: 2.4
Name: db-model-trainer
Version: 0.1.2
Summary: A package for processing YAML in Databricks
Home-page: https://github.com/BenMacKenzie/db-model-trainer.git
Author: Ben Mackenzie
Author-email: Ben Mackenzie <ben.mackenzie@example.com>
License: MIT
Project-URL: Homepage, https://github.com/yourusername/db-model-trainer
Project-URL: Bug Tracker, https://github.com/yourusername/db-model-trainer/issues
Classifier: Programming Language :: Python :: 3
Classifier: Operating System :: OS Independent
Classifier: Development Status :: 3 - Alpha
Classifier: Intended Audience :: Developers
Classifier: Topic :: Software Development :: Libraries :: Python Modules
Requires-Python: >=3.7
License-File: LICENSE
Requires-Dist: pyyaml>=6.0.1
Requires-Dist: click>=8.0.0
Dynamic: author
Dynamic: home-page
Dynamic: license-file
Dynamic: requires-python
